feed2exec/__init__.py
feed2exec/__main__.py
feed2exec/_version.py
feed2exec/controller.py
feed2exec/email.py
feed2exec/logging.py
feed2exec/model.py
feed2exec/utils.py
feed2exec/plugins/__init__.py
feed2exec/plugins/archive.py
feed2exec/plugins/droptitle.py
feed2exec/plugins/droptitleregex.py
feed2exec/plugins/echo.py
feed2exec/plugins/emptysummary.py
feed2exec/plugins/error.py
feed2exec/plugins/exec.py
feed2exec/plugins/html2text.py
feed2exec/plugins/ikiwiki_recentchanges.py
feed2exec/plugins/ikiwikitoot.py
feed2exec/plugins/json.py
feed2exec/plugins/maildir.py
feed2exec/plugins/matchtitleregex.py
feed2exec/plugins/mbox.py
feed2exec/plugins/null.py
feed2exec/plugins/transmission.py
feed2exec/plugins/wayback.py
feed2exec/tests/__init__.py
feed2exec/tests/conftest.py
feed2exec/tests/pytest.ini
feed2exec/tests/test_feeds.py
feed2exec/tests/test_main.py
feed2exec/tests/test_network.py
feed2exec/tests/test_opml.py
feed2exec/tests/test_plugins.py
feed2exec/tests/cassettes/feed2exec.tests.test_feeds.test_add.json
feed2exec/tests/cassettes/feed2exec.tests.test_feeds.test_cache.json
feed2exec/tests/cassettes/feed2exec.tests.test_feeds.test_fetch.json
feed2exec/tests/cassettes/feed2exec.tests.test_feeds.test_fetch_cache.json
feed2exec/tests/cassettes/feed2exec.tests.test_feeds.test_fetch_parallel.json
feed2exec/tests/cassettes/feed2exec.tests.test_feeds.test_normalize.json
feed2exec/tests/cassettes/feed2exec.tests.test_feeds.test_pattern.json
feed2exec/tests/cassettes/feed2exec.tests.test_feeds.test_settings.json
feed2exec/tests/cassettes/feed2exec.tests.test_main.test_basics.json
feed2exec/tests/cassettes/feed2exec.tests.test_main.test_parse.json
feed2exec/tests/cassettes/feed2exec.tests.test_main.test_planet.json
feed2exec/tests/cassettes/feed2exec.tests.test_opml.test_opml.json
feed2exec/tests/cassettes/feed2exec.tests.test_plugins.test_archive.json
feed2exec/tests/cassettes/feed2exec.tests.test_plugins.test_email.json
feed2exec-0.22.0.dist-info/LICENSE.rst
feed2exec-0.22.0.dist-info/METADATA
feed2exec-0.22.0.dist-info/WHEEL
feed2exec-0.22.0.dist-info/entry_points.txt
feed2exec-0.22.0.dist-info/top_level.txt
feed2exec-0.22.0.dist-info/RECORD
