Metadata-Version: 2.2
Name: feed2exec
Version: 0.22.0
Summary: The programmable feed reader
Author-email: anarcat@debian.org
License: AGPLv3
Project-URL: homepage, https://gitlab.com/anarcat/feed2exec
Project-URL: documentation, https://feed2exec.readthedocs.io
Classifier: Development Status :: 4 - Beta
Classifier: Environment :: Console
Classifier: Intended Audience :: End Users/Desktop
Classifier: Intended Audience :: System Administrators
Classifier: License :: OSI Approved :: GNU Affero General Public License v3 or later (AGPLv3+)
Classifier: Natural Language :: English
Classifier: Operating System :: POSIX
Classifier: Operating System :: POSIX :: Linux
Classifier: Programming Language :: Python
Classifier: Programming Language :: Python :: 3
Classifier: Programming Language :: Python :: 3.8
Classifier: Programming Language :: Python :: 3.9
Classifier: Programming Language :: Python :: 3.10
Classifier: Topic :: Communications :: Email
Classifier: Topic :: Internet :: WWW/HTTP :: Dynamic Content :: News/Diary
Classifier: Topic :: Text Processing :: Markup :: HTML
License-File: LICENSE.rst
Requires-Dist: cachecontrol
Requires-Dist: click
Requires-Dist: dateparser
Requires-Dist: feedparser>=6.0.0b3; python_version >= "3.6"
Requires-Dist: html2text
Requires-Dist: html5lib
Requires-Dist: lxml
Requires-Dist: pyxdg
Requires-Dist: requests
Requires-Dist: requests-file
Requires-Dist: setuptools_scm
Requires-Dist: unidecode
Provides-Extra: test
Requires-Dist: betamax>=0.8.0; extra == "test"
Requires-Dist: pyflakes; extra == "test"
Requires-Dist: pytest; extra == "test"
Requires-Dist: pytest-cov; extra == "test"
Requires-Dist: tox; extra == "test"
